LICENSE.txt
MANIFEST.in
README.rst
setup.py
docs/Makefile
docs/conf.py
docs/index.rst
docs/workflow_templatesRemoteActionCreditLimitTestWF.xlsx
docs/_build/html/_downloads/37f561b29cb931d58b524e1fa6a2d932/AP_Invoice_Batch_Adobe_Sign_Workflow.xlsx
docs/_build/html/_images/02_email_message_template.png
docs/_build/html/_images/03_basic_setup.png
docs/_build/html/_images/04_add_step.png
docs/_build/html/_images/05_set_script.png
docs/_build/html/_images/06_open_task_scheduler.png
docs/_build/html/_images/07_create_task.png
docs/_build/html/_images/08_edit_trigger.png
docs/_build/html/_images/09_edit_action.png
docs/_build/html/_images/10_task_settings.png
docs/_build/html/_static/comment-bright.png
docs/_build/html/_static/comment-close.png
docs/_build/html/_static/comment.png
docs/_build/html/_static/down-pressed.png
docs/_build/html/_static/down.png
docs/_build/html/_static/file.png
docs/_build/html/_static/minus.png
docs/_build/html/_static/plus.png
docs/_build/html/_static/up-pressed.png
docs/_build/html/_static/up.png
docs/images/adobe-sign/01-adobe-sign-developer-signup.png
docs/images/adobe-sign/02-adobe-sign-application-create.png
docs/images/adobe-sign/02-shard.png
docs/images/adobe-sign/03-adobe-sign-configure-application.png
docs/images/adobe-sign/04-adobe-sign-configure-oauth-link.png
docs/images/adobe-sign/05-adobe-sign-configure-oauth.png
docs/images/adobe-sign/06-adobe-sign-connect.png
docs/images/adobe-sign/07-adobe-sign-connect-empty.png
docs/images/adobe-sign/08-adobe-sign-connect-authorize.png
docs/images/adobe-sign/09-adobe-sign-connect-codes.png
docs/images/adobe-sign/10-adobe-sign-connect-connect.png
docs/images/adobe-sign/11-adobe-sign-connect-connected.png
docs/images/psched/02_email_message_template.png
docs/images/psched/03_basic_setup.png
docs/images/psched/04_add_step.png
docs/images/psched/05_set_script.png
docs/images/psched/06_open_task_scheduler.png
docs/images/psched/07_create_task.png
docs/images/psched/08_edit_trigger.png
remote_actions.egg-info/PKG-INFO
remote_actions.egg-info/SOURCES.txt
remote_actions.egg-info/dependency_links.txt
remote_actions.egg-info/requires.txt
remote_actions.egg-info/top_level.txt
