Metadata-Version: 2.1
Name: remote-actions
Version: 6.0.18
Summary: Remote Action for Orchid Extender
Home-page: https://poplars.dev
Author: Chris Binckly, Poplar Development
Author-email: chris@poplars.dev
License: UNKNOWN
Keywords: sage orchid extender remote approvals
Platform: UNKNOWN
Classifier: Development Status :: 4 - Beta
Classifier: Intended Audience :: Developers
Classifier: Topic :: Software Development :: Build Tools
Classifier: Environment :: Win32 (MS Windows)
Classifier: Operating System :: Microsoft :: Windows
Classifier: Programming Language :: Python :: 3.4
Classifier: License :: OSI Approved :: GNU General Public License v3 (GPLv3)
